[{"author":"qwert","title":"a blog for code","body":"bahr bhar ke code","code":"haha code"},{"author":"qwertyuu","title":"a blog for abcersdsdd code","body":"body newr ke code","code":"new code"},{"author":"qwewewewe","title":"","body":"","code":""},{"author":"qwqqwqwqw","title":"a blog for abcersdsdd codeone","body":"body newr ke code","code":"new codeone"},{"author":"qwqwqwqwqwqwqw","title":"a blog for abcersdsdd two","body":"body newr ke two","code":"new two"},{"author":"qwqwqwqwqwqwqw","title":"","body":"","code":""},{"author":"qwqwqwqwqwqwqw","title":"baap1 a blog for abcersdsdd two","body":"body newr ke two","code":"new two"}]